yoohoo/__init__.py
yoohoo-0.0.3.dist-info/LICENSE
yoohoo-0.0.3.dist-info/METADATA
yoohoo-0.0.3.dist-info/WHEEL
yoohoo-0.0.3.dist-info/top_level.txt
yoohoo-0.0.3.dist-info/RECORD
